Metadata-Version: 1.0
Name: rogin-gaussian-binomial
Version: 0.1
Summary: Gaussian and Binomial distributions
Home-page: UNKNOWN
Author: Rogin Koshy
Author-email: rgkss13@gmail.com
License: UNKNOWN
Platform: UNKNOWN
